Workbook

Sheet Cover & Methodology
A1: Banco Santander, S.A. and Subsidiaries — Consolidated FP&A Workbook
A2: Income statement, balance sheet, equity roll-forward and reconstructed (direct & indirect) cash flow — FY2025 vs FY2024 (FY2023 shown as comparative on the balance sheet)
A4: 1. Source document and language
A5: All figures in this workbook are transcribed from Banco Santander, S.A.'s Spanish-language 2025 Annual Report ("Informe anual 2025"), consolidated financial statements section ("Estados financieros consolidados"), covering the balances at 31 December 2025, 2024 and 2023 and the income statement, statement of recognised income and expense, and statement of total changes in equity for the years then ended. No English-language version of the financial statements was available at the time this workbook was prepared; all line-item labels have been translated from Spanish to English by the workbook's author. The underlying figures have not been altered in any way — only translated in label and re-expressed in units (see note 2).
A6: 2024 and 2023 balance sheet figures are labelled "A" in the source report, meaning they are presented solely for comparative purposes (see source note 1.d) and may reflect re-presentation versus how they were originally reported in the FY2024 and FY2023 annual reports.
A8: 2. Units and rounding
A9: The source financial statements are reported in EUR MILLIONS, rounded to the nearest million. This workbook re-expresses every figure in EUR THOUSANDS by multiplying the reported million figure by 1,000 (e.g. EUR 152,281 million becomes EUR 152,281,000 thousand). This is a pure unit conversion, not a change in precision: because the source itself is only precise to the nearest EUR million, every thousands-figure in this workbook necessarily ends in '000'. No additional decimal precision is implied or has been invented.
A10: All amounts are shown with zero decimal places. Negative amounts are shown in parentheses.
A12: 3. What is hardcoded vs. calculated
A13: Blue font = figures transcribed directly from the source financial statements (hardcoded inputs, with a page citation in the Source column of each tab). Black font = formulas that sum or subtotal the blue inputs on the same tab. Green font = formulas that link to a figure on another tab. Nothing in this workbook is a plug, a forced balancing entry, or an estimate not traceable to a disclosed source figure, with the single, clearly-labelled exception described in note 5 below.
A15: 4. Equity detail — retained earnings vs. net income
A16: Per your request, retained earnings ("Ganancias acumuladas") are shown as a separate line from net income attributable to the parent ("Resultado atribuible a los propietarios de la dominante") on both the Balance Sheet tab and the Equity Rollforward tab, exactly as the source statements present them — these have never been the same line in Banco Santander's own statements, so no adjustment was needed to achieve this separation.
... A28: Every figure with blue font can be traced to the Source column citation on its row. Every subtotal and total is a SUM formula over the rows above it — recompute by expanding the formula bar. Every cash-flow line on the Direct Cash Flow tab that should equal its Indirect Cash Flow counterpart is linked by formula, not retyped, so the two tabs cannot silently drift apart. The final reconciliation section on each cash flow tab shows opening cash, the reconstructed net movement, the unreconciled bridge, and closing cash — the closing cash row should always equal, and does equal by construction, the cash balance reported on the Balance Sheet tab for the same year.

Sheet P&L
A1: Banco Santander — Consolidated Income Statement
A2: Years ended 31 December 2025, 2024 and 2023
A3: Figures in EUR thousands, unless otherwise stated. No decimals shown.
A5: Line item | B5: Note | C5: FY2025 | D5: FY2024 | E5: FY2023 | F5: Source / notes
A6: Interest income | B6: 38 | C6: 101710000 | D6: 109012000 | E6: 101742000 | F6: Source: Banco Santander, Informe anual 2025, Cuentas de perdidas y ganancias consolidadas, p.653-654 (ES); EUR mn x1,000
A7: Financial assets at fair value through other comprehensive income | C7: 5713000 | D7: 6931000 | E7: 5533000 | F7: Source: Banco Santander, Informe anual 2025, Cuentas de perdidas y ganancias consolidadas, p.653-654 (ES); EUR mn x1,000
A8: Financial assets at amortised cost | C8: 76248000 | D8: 80992000 | E8: 74799000 | F8: Source: Banco Santander, Informe anual 2025, Cuentas de perdidas y ganancias consolidadas, p.653-654 (ES); EUR mn x1,000
A9: Other interest income | C9: 19749000 | D9: 21089000 | E9: 21410000 | F9: Source: Banco Santander, Informe anual 2025, Cuentas de perdidas y ganancias consolidadas, p.653-654 (ES); EUR mn x1,000
A10: Interest expense | B10: 39 | C10: -59362000 | D10: -65225000 | E10: -61092000 | F10: Source: Banco Santander, Informe anual 2025, Cuentas de perdidas y ganancias consolidadas, p.653-654 (ES); EUR mn x1,000
A11: Net interest income | C11: 42348000 | D11: 43787000 | E11: 40650000 | F11: Source: Banco Santander, Informe anual 2025, Cuentas de perdidas y ganancias consolidadas, p.653-654 (ES); EUR mn x1,000
A12: Dividend income | B12: 40 | C12: 715000 | D12: 710000 | E12: 568000 | F12: Source: Banco Santander, Informe anual 2025, Cuentas de perdidas y ganancias consolidadas, p.653-654 (ES); EUR mn x1,000
A13: Share of results of entities accounted for using the equity method | B13: 13 | C13: 665000 | D13: 687000 | E13: 591000 | F13: Source: Banco Santander, Informe anual 2025, Cuentas de perdidas y ganancias consolidadas, p.653-654 (ES); EUR mn x1,000
A14: Fee and commission income | B14: 41 | C14: 17387000 | D14: 16834000 | E14: 15644000 | F14: Source: Banco Santander, Informe anual 2025, Cuentas de perdidas y ganancias consolidadas, p.653-654 (ES); EUR mn x1,000
A15: Fee and commission expense | B15: 42 | C15: -4411000 | D15: -4458000 | E15: -4149000 | F15: Source: Banco Santander, Informe anual 2025, Cuentas de perdidas y ganancias consolidadas, p.653-654 (ES); EUR mn x1,000
A16: Gains/(losses) on derecognition of financial assets/liabilities not at FVTPL, net | B16: 43 | C16: 127000 | D16: -117000 | E16: 96000 | F16: Source: Banco Santander, Informe anual 2025, Cuentas de perdidas y ganancias consolidadas, p.653-654 (ES); EUR mn x1,000
A17: Financial assets at amortised cost | C17: -89000 | D17: -190000 | E17: -3000 | F17: Source: Banco Santander, Informe anual 2025, Cuentas de perdidas y ganancias consolidadas, p.653-654 (ES); EUR mn x1,000
A18: Other financial assets and liabilities | C18: 216000 | D18: 73000 | E18: 99000 | F18: Source: Banco Santander, Informe anual 2025, Cuentas de perdidas y ganancias consolidadas, p.653-654 (ES); EUR mn x1,000
A19: Gains/(losses) on financial assets/liabilities held for trading, net | B19: 43 | C19: 1017000 | D19: 1344000 | E19: 2316000 | F19: Source: Banco Santander, Informe anual 2025, Cuentas de perdidas y ganancias consolidadas, p.653-654 (ES); EUR mn x1,000
A20: Gains/(losses) on non-trading financial assets mandatorily at FVTPL, net | B20: 43 | C20: 1106000 | D20: 495000 | E20: 198000 | F20: Source: Banco Santander, Informe anual 2025, Cuentas de perdidas y ganancias consolidadas, p.653-654 (ES); EUR mn x1,000
A21: Gains/(losses) on financial assets/liabilities designated at FVTPL, net | B21: 43 | C21: -307000 | D21: 691000 | E21: -92000 | F21: Source: Banco Santander, Informe anual 2025, Cuentas de perdidas y ganancias consolidadas, p.653-654 (ES); EUR mn x1,000
A22: Gains/(losses) from hedge accounting, net | B22: 43 | C22: 12000 | D22: 14000 | E22: 69000 | F22: Source: Banco Santander, Informe anual 2025, Cuentas de perdidas y ganancias consolidadas, p.653-654 (ES); EUR mn x1,000
A23: Exchange differences, net | B23: 44 | C23: 407000 | D23: -216000 | E23: -22000 | F23: Source: Banco Santander, Informe anual 2025, Cuentas de perdidas y ganancias consolidadas, p.653-654 (ES); EUR mn x1,000
A24: Other operating income | B24: 45 | C24: 1583000 | D24: 846000 | E24: 1137000 | F24: Source: Banco Santander, Informe anual 2025, Cuentas de perdidas y ganancias consolidadas, p.653-654 (ES); EUR mn x1,000
A25: Other operating expenses | B25: 45 | C25: -2070000 | D25: -2258000 | E25: -2766000 | F25: Source: Banco Santander, Informe anual 2025, Cuentas de perdidas y ganancias consolidadas, p.653-654 (ES); EUR mn x1,000
A26: Income from insurance or reinsurance contracts | C26: 476000 | D26: 470000 | E26: 460000 | F26: Source: Banco Santander, Informe anual 2025, Cuentas de perdidas y ganancias consolidadas, p.653-654 (ES); EUR mn x1,000
A27: Expenses from insurance or reinsurance contracts | C27: -385000 | D27: -449000 | E27: -449000 | F27: Source: Banco Santander, Informe anual 2025, Cuentas de perdidas y ganancias consolidadas, p.653-654 (ES); EUR mn x1,000
A28: Gross income | C28: 58670000 | D28: 58380000 | E28: 54251000 | F28: Source: Banco Santander, Informe anual 2025, Cuentas de perdidas y ganancias consolidadas, p.653-654 (ES); EUR mn x1,000
A29: Administrative expenses | C29: -21533000 | D29: -21970000 | E29: -21546000 | F29: Source: Banco Santander, Informe anual 2025, Cuentas de perdidas y ganancias consolidadas, p.653-654 (ES); EUR mn x1,000
A30: Staff costs | B30: 46 | C30: -13633000 | D30: -13825000 | E30: -13275000 | F30: Source: Banco Santander, Informe anual 2025, Cuentas de perdidas y ganancias consolidadas, p.653-654 (ES); EUR mn x1,000
A31: Other administrative expenses | B31: 47 | C31: -7900000 | D31: -8145000 | E31: -8271000 | F31: Source: Banco Santander, Informe anual 2025, Cuentas de perdidas y ganancias consolidadas, p.653-654 (ES); EUR mn x1,000
A32: Depreciation and amortisation | B32: 16, 18 | C32: -3178000 | D32: -3179000 | E32: -3086000 | F32: Source: Banco Santander, Informe anual 2025, Cuentas de perdidas y ganancias consolidadas, p.653-654 (ES); EUR mn x1,000
A33: Provisions or reversal of provisions, net | B33: 25 | C33: -2729000 | D33: -3465000 | E33: -2410000 | F33: Source: Banco Santander, Informe anual 2025, Cuentas de perdidas y ganancias consolidadas, p.653-654 (ES); EUR mn x1,000
A34: Impairment of financial assets not at FVTPL and net gains/(losses) on modification | C34: -12546000 | D34: -12136000 | E34: -12298000 | F34: Source: Banco Santander, Informe anual 2025, Cuentas de perdidas y ganancias consolidadas, p.653-654 (ES); EUR mn x1,000
A35: Financial assets at fair value through other comprehensive income | C35: -29000 | D35: 1000 | E35: -24000 | F35: Source: Banco Santander, Informe anual 2025, Cuentas de perdidas y ganancias consolidadas, p.653-654 (ES); EUR mn x1,000
A36: Financial assets at amortised cost | B36: 10 | C36: -12517000 | D36: -12137000 | E36: -12274000 | F36: Source: Banco Santander, Informe anual 2025, Cuentas de perdidas y ganancias consolidadas, p.653-654 (ES); EUR mn x1,000
A37: Impairment/(reversal) of investments in joint ventures or associates | B37: 13, 18 | C37: 0 | D37: 0 | E37: 0 | F37: Source: Banco Santander, Informe anual 2025, Cuentas de perdidas y ganancias consolidadas, p.653-654 (ES); EUR mn x1,000
A38: Impairment/(reversal) of non-financial assets | C38: -251000 | D38: -624000 | E38: -237000 | F38: Source: Banco Santander, Informe anual 2025, Cuentas de perdidas y ganancias consolidadas, p.653-654 (ES); EUR mn x1,000
A39: Tangible assets | B39: 16 | C39: -129000 | D39: -382000 | E39: -135000 | F39: Source: Banco Santander, Informe anual 2025, Cuentas de perdidas y ganancias consolidadas, p.653-654 (ES); EUR mn x1,000
A40: Intangible assets | B40: 17, 18 | C40: -112000 | D40: -231000 | E40: -73000 | F40: Source: Banco Santander, Informe anual 2025, Cuentas de perdidas y ganancias consolidadas, p.653-654 (ES); EUR mn x1,000
A41: Other | C41: -10000 | D41: -11000 | E41: -29000 | F41: Source: Banco Santander, Informe anual 2025, Cuentas de perdidas y ganancias consolidadas, p.653-654 (ES); EUR mn x1,000
A42: Gains/(losses) on derecognition of non-financial assets, net | B42: 48 | C42: 0 | D42: 368000 | E42: 312000 | F42: Source: Banco Santander, Informe anual 2025, Cuentas de perdidas y ganancias consolidadas, p.653-654 (ES); EUR mn x1,000
A43: Negative goodwill recognised in profit or loss | C43: 22000 | D43: 0 | E43: 39000 | F43: Source: Banco Santander, Informe anual 2025, Cuentas de perdidas y ganancias consolidadas, p.653-654 (ES); EUR mn x1,000
A44: Gains/(losses) from non-current assets held for sale not classified as discontinued operations | B44: 49 | C44: 226000 | D44: -27000 | E44: -20000 | F44: Source: Banco Santander, Informe anual 2025, Cuentas de perdidas y ganancias consolidadas, p.653-654 (ES); EUR mn x1,000
A45: Profit before tax from continuing operations | C45: 18681000 | D45: 17347000 | E45: 15005000 | F45: Source: Banco Santander, Informe anual 2025, Cuentas de perdidas y ganancias consolidadas, p.653-654 (ES); EUR mn x1,000
A46: Tax expense on profit from continuing operations | B46: 27 | C46: -4723000 | D46: -4844000 | E46: -3880000 | F46: Source: Banco Santander, Informe anual 2025, Cuentas de perdidas y ganancias consolidadas, p.653-654 (ES); EUR mn x1,000
A47: Profit after tax from continuing operations | C47: 13958000 | D47: 12503000 | E47: 11125000 | F47: Source: Banco Santander, Informe anual 2025, Cuentas de perdidas y ganancias consolidadas, p.653-654 (ES); EUR mn x1,000
A48: Profit after tax from discontinued operations | B48: 37 | C48: 1542000 | D48: 1241000 | E48: 1058000 | F48: Source: Banco Santander, Informe anual 2025, Cuentas de perdidas y ganancias consolidadas, p.653-654 (ES); EUR mn x1,000
A49: Profit for the year (consolidated) | C49: 15500000 | D49: 13744000 | E49: 12183000 | F49: Source: Banco Santander, Informe anual 2025, Cuentas de perdidas y ganancias consolidadas, p.653-654 (ES); EUR mn x1,000
A50: Attributable to non-controlling interests | B50: 28 | C50: 1399000 | D50: 1170000 | E50: 1107000 | F50: Source: Banco Santander, Informe anual 2025, Cuentas de perdidas y ganancias consolidadas, p.653-654 (ES); EUR mn x1,000
A51: Attributable to owners of the parent (net income) | C51: 14101000 | D51: 12574000 | E51: 11076000 | F51: Source: Banco Santander, Informe anual 2025, Cuentas de perdidas y ganancias consolidadas, p.653-654 (ES); EUR mn x1,000
A53: MEMO: EARNINGS PER SHARE (EUR, not thousands)
A54: Basic earnings per share (EUR) | B54: 4 | C54: 0.905 | D54: 0.771 | E54: 0.654 | F54: Source: Banco Santander, Informe anual 2025, Cuentas de perdidas y ganancias consolidadas, p.653-654 (ES); EUR mn x1,000
A55: Diluted earnings per share (EUR) | B55: 4 | C55: 0.9 | D55: 0.768 | E55: 0.651 | F55: Source: Banco Santander, Informe anual 2025, Cuentas de perdidas y ganancias consolidadas, p.653-654 (ES); EUR mn x1,000

Sheet Balance Sheet
A1: Banco Santander — Consolidated Balance Sheet
A2: As at 31 December 2025, 2024 and 2023
A3: Figures in EUR thousands, unless otherwise stated. No decimals shown.
A5: Line item | B5: Note | C5: FY2025 | D5: FY2024 | E5: FY2023 | F5: Source / notes
A6: ASSETS
A7: Cash, cash balances at central banks and other demand deposits | C7: 152281000 | D7: 192208000 | E7: 220342000 | F7: Source: Banco Santander, Informe anual 2025, Balances consolidados, p.649-650 (ES); EUR mn x1,000
A8: Financial assets held for trading | C8: 252318000 | D8: 230253000 | E8: 176921000 | F8: Source: Banco Santander, Informe anual 2025, Balances consolidados, p.649-650 (ES); EUR mn x1,000
A9: Derivatives | B9: 9, 11 | C9: 58355000 | D9: 64100000 | E9: 56328000 | F9: Source: Banco Santander, Informe anual 2025, Balances consolidados, p.649-650 (ES); EUR mn x1,000
A10: Equity instruments | B10: 8 | C10: 22030000 | D10: 16636000 | E10: 15057000 | F10: Source: Banco Santander, Informe anual 2025, Balances consolidados, p.649-650 (ES); EUR mn x1,000
A11: Debt securities | B11: 7 | C11: 98568000 | D11: 82646000 | E11: 62124000 | F11: Source: Banco Santander, Informe anual 2025, Balances consolidados, p.649-650 (ES); EUR mn x1,000
A12: Loans and advances | C12: 73365000 | D12: 66871000 | E12: 43412000 | F12: Source: Banco Santander, Informe anual 2025, Balances consolidados, p.649-650 (ES); EUR mn x1,000
A13: Central banks | B13: 6 | C13: 14632000 | D13: 12966000 | E13: 17717000 | F13: Source: Banco Santander, Informe anual 2025, Balances consolidados, p.649-650 (ES); EUR mn x1,000
A14: Credit institutions | B14: 6 | C14: 25967000 | D14: 27314000 | E14: 14061000 | F14: Source: Banco Santander, Informe anual 2025, Balances consolidados, p.649-650 (ES); EUR mn x1,000
A15: Customers | B15: 10 | C15: 32766000 | D15: 26591000 | E15: 11634000 | F15: Source: Banco Santander, Informe anual 2025, Balances consolidados, p.649-650 (ES); EUR mn x1,000
A16: Non-trading financial assets mandatorily at fair value through profit or loss | C16: 7761000 | D16: 6130000 | E16: 5910000 | F16: Source: Banco Santander, Informe anual 2025, Balances consolidados, p.649-650 (ES); EUR mn x1,000
A17: Equity instruments | B17: 8 | C17: 5815000 | D17: 4641000 | E17: 4068000 | F17: Source: Banco Santander, Informe anual 2025, Balances consolidados, p.649-650 (ES); EUR mn x1,000
A18: Debt securities | B18: 7 | C18: 245000 | D18: 447000 | E18: 860000 | F18: Source: Banco Santander, Informe anual 2025, Balances consolidados, p.649-650 (ES); EUR mn x1,000
A19: Loans and advances | C19: 1701000 | D19: 1042000 | E19: 982000 | F19: Source: Banco Santander, Informe anual 2025, Balances consolidados, p.649-650 (ES); EUR mn x1,000
A20: Central banks | B20: 6 | C20: 0 | D20: 0 | E20: 0 | F20: Source: Banco Santander, Informe anual 2025, Balances consolidados, p.649-650 (ES); EUR mn x1,000
A21: Credit institutions | B21: 6 | C21: 0 | D21: 0 | E21: 0 | F21: Source: Banco Santander, Informe anual 2025, Balances consolidados, p.649-650 (ES); EUR mn x1,000
A22: Customers | B22: 10 | C22: 1701000 | D22: 1042000 | E22: 982000 | F22: Source: Banco Santander, Informe anual 2025, Balances consolidados, p.649-650 (ES); EUR mn x1,000
A23: Financial assets designated at fair value through profit or loss | C23: 8046000 | D23: 7915000 | E23: 9773000 | F23: Source: Banco Santander, Informe anual 2025, Balances consolidados, p.649-650 (ES); EUR mn x1,000
A24: Debt securities | B24: 7 | C24: 2894000 | D24: 2897000 | E24: 3095000 | F24: Source: Banco Santander, Informe anual 2025, Balances consolidados, p.649-650 (ES); EUR mn x1,000
A25: Loans and advances | C25: 5152000 | D25: 5018000 | E25: 6678000 | F25: Source: Banco Santander, Informe anual 2025, Balances consolidados, p.649-650 (ES); EUR mn x1,000
A26: Central banks | B26: 6 | C26: 0 | D26: 0 | E26: 0 | F26: Source: Banco Santander, Informe anual 2025, Balances consolidados, p.649-650 (ES); EUR mn x1,000
A27: Credit institutions | B27: 6 | C27: 413000 | D27: 408000 | E27: 459000 | F27: Source: Banco Santander, Informe anual 2025, Balances consolidados, p.649-650 (ES); EUR mn x1,000
A28: Customers | B28: 10 | C28: 4739000 | D28: 4610000 | E28: 6219000 | F28: Source: Banco Santander, Informe anual 2025, Balances consolidados, p.649-650 (ES); EUR mn x1,000
A29: Financial assets at fair value through other comprehensive income | C29: 74612000 | D29: 89898000 | E29: 83308000 | F29: Source: Banco Santander, Informe anual 2025, Balances consolidados, p.649-650 (ES); EUR mn x1,000
A30: Equity instruments | B30: 8 | C30: 2281000 | D30: 2193000 | E30: 1761000 | F30: Source: Banco Santander, Informe anual 2025, Balances consolidados, p.649-650 (ES); EUR mn x1,000
A31: Debt securities | B31: 7 | C31: 58305000 | D31: 76558000 | E31: 73565000 | F31: Source: Banco Santander, Informe anual 2025, Balances consolidados, p.649-650 (ES); EUR mn x1,000
A32: Loans and advances | C32: 14026000 | D32: 11147000 | E32: 7982000 | F32: Source: Banco Santander, Informe anual 2025, Balances consolidados, p.649-650 (ES); EUR mn x1,000
A33: Central banks | B33: 6 | C33: 0 | D33: 0 | E33: 0 | F33: Source: Banco Santander, Informe anual 2025, Balances consolidados, p.649-650 (ES); EUR mn x1,000
A34: Credit institutions | B34: 6 | C34: 1120000 | D34: 363000 | E34: 313000 | F34: Source: Banco Santander, Informe anual 2025, Balances consolidados, p.649-650 (ES); EUR mn x1,000
A35: Customers | B35: 10 | C35: 12906000 | D35: 10784000 | E35: 7669000 | F35: Source: Banco Santander, Informe anual 2025, Balances consolidados, p.649-650 (ES); EUR mn x1,000
A36: Financial assets at amortised cost | C36: 1202689000 | D36: 1203707000 | E36: 1191403000 | F36: Source: Banco Santander, Informe anual 2025, Balances consolidados, p.649-650 (ES); EUR mn x1,000
A37: Debt securities | B37: 7 | C37: 140014000 | D37: 120949000 | E37: 103559000 | F37: Source: Banco Santander, Informe anual 2025, Balances consolidados, p.649-650 (ES); EUR mn x1,000
A38: Loans and advances | C38: 1062675000 | D38: 1082758000 | E38: 1087844000 | F38: Source: Banco Santander, Informe anual 2025, Balances consolidados, p.649-650 (ES); EUR mn x1,000
A39: Central banks | B39: 6 | C39: 15986000 | D39: 16179000 | E39: 20082000 | F39: Source: Banco Santander, Informe anual 2025, Balances consolidados, p.649-650 (ES); EUR mn x1,000
A40: Credit institutions | B40: 6 | C40: 61513000 | D40: 55537000 | E40: 57917000 | F40: Source: Banco Santander, Informe anual 2025, Balances consolidados, p.649-650 (ES); EUR mn x1,000
A41: Customers | B41: 10 | C41: 985176000 | D41: 1011042000 | E41: 1009845000 | F41: Source: Banco Santander, Informe anual 2025, Balances consolidados, p.649-650 (ES); EUR mn x1,000
A42: Hedging derivatives | B42: 36 | C42: 3931000 | D42: 5672000 | E42: 5297000 | F42: Source: Banco Santander, Informe anual 2025, Balances consolidados, p.649-650 (ES); EUR mn x1,000
A43: Fair value changes of hedged items in portfolio hedge of interest rate risk | B43: 54 | C43: 50000 | D43: -704000 | E43: -788000 | F43: Source: Banco Santander, Informe anual 2025, Balances consolidados, p.649-650 (ES); EUR mn x1,000
A44: Investments in joint ventures and associates | B44: 13 | C44: 7052000 | D44: 7277000 | E44: 7646000 | F44: Source: Banco Santander, Informe anual 2025, Balances consolidados, p.649-650 (ES); EUR mn x1,000
A45: Joint ventures | C45: 1956000 | D45: 2061000 | E45: 1964000 | F45: Source: Banco Santander, Informe anual 2025, Balances consolidados, p.649-650 (ES); EUR mn x1,000
A46: Associates | C46: 5096000 | D46: 5216000 | E46: 5682000 | F46: Source: Banco Santander, Informe anual 2025, Balances consolidados, p.649-650 (ES); EUR mn x1,000
A47: Assets under reinsurance contracts | C47: 223000 | D47: 222000 | E47: 237000 | F47: Source: Banco Santander, Informe anual 2025, Balances consolidados, p.649-650 (ES); EUR mn x1,000
A48: Tangible assets | C48: 27438000 | D48: 32087000 | E48: 33882000 | F48: Source: Banco Santander, Informe anual 2025, Balances consolidados, p.649-650 (ES); EUR mn x1,000
A49: Property, plant and equipment | B49: 16 | C49: 26416000 | D49: 31212000 | E49: 32926000 | F49: Source: Banco Santander, Informe anual 2025, Balances consolidados, p.649-650 (ES); EUR mn x1,000
A50: For own use | C50: 11663000 | D50: 12636000 | E50: 13408000 | F50: Source: Banco Santander, Informe anual 2025, Balances consolidados, p.649-650 (ES); EUR mn x1,000
A51: Leased out under operating lease | C51: 14753000 | D51: 18576000 | E51: 19518000 | F51: Source: Banco Santander, Informe anual 2025, Balances consolidados, p.649-650 (ES); EUR mn x1,000
A52: Investment property | B52: 16 | C52: 1022000 | D52: 875000 | E52: 956000 | F52: Source: Banco Santander, Informe anual 2025, Balances consolidados, p.649-650 (ES); EUR mn x1,000
A53: Of which: leased out under operating lease | C53: 860000 | D53: 749000 | E53: 851000 | F53: Source: Banco Santander, Informe anual 2025, Balances consolidados, p.649-650 (ES); EUR mn x1,000
A54: Intangible assets | C54: 17308000 | D54: 19259000 | E54: 19871000 | F54: Source: Banco Santander, Informe anual 2025, Balances consolidados, p.649-650 (ES); EUR mn x1,000
A55: Goodwill | B55: 17 | C55: 11958000 | D55: 13438000 | E55: 14017000 | F55: Source: Banco Santander, Informe anual 2025, Balances consolidados, p.649-650 (ES); EUR mn x1,000
A56: Other intangible assets | B56: 18 | C56: 5350000 | D56: 5821000 | E56: 5854000 | F56: Source: Banco Santander, Informe anual 2025, Balances consolidados, p.649-650 (ES); EUR mn x1,000
A57: Tax assets | C57: 30076000 | D57: 30596000 | E57: 31390000 | F57: Source: Banco Santander, Informe anual 2025, Balances consolidados, p.649-650 (ES); EUR mn x1,000
A58: Current tax assets | C58: 11132000 | D58: 11426000 | E58: 10623000 | F58: Source: Banco Santander, Informe anual 2025, Balances consolidados, p.649-650 (ES); EUR mn x1,000
A59: Deferred tax assets | B59: 27 | C59: 18944000 | D59: 19170000 | E59: 20767000 | F59: Source: Banco Santander, Informe anual 2025, Balances consolidados, p.649-650 (ES); EUR mn x1,000
A60: Other assets | C60: 8719000 | D60: 8559000 | E60: 8856000 | F60: Source: Banco Santander, Informe anual 2025, Balances consolidados, p.649-650 (ES); EUR mn x1,000
A61: Insurance contracts linked to pensions | B61: 14 | C61: 67000 | D61: 81000 | E61: 93000 | F61: Source: Banco Santander, Informe anual 2025, Balances consolidados, p.649-650 (ES); EUR mn x1,000
A62: Inventories | C62: 7000 | D62: 6000 | E62: 7000 | F62: Source: Banco Santander, Informe anual 2025, Balances consolidados, p.649-650 (ES); EUR mn x1,000
A63: Rest of other assets | B63: 19 | C63: 8645000 | D63: 8472000 | E63: 8756000 | F63: Source: Banco Santander, Informe anual 2025, Balances consolidados, p.649-650 (ES); EUR mn x1,000
A64: Non-current assets and disposal groups classified as held for sale | B64: 12 | C64: 75011000 | D64: 4002000 | E64: 3014000 | F64: Source: Banco Santander, Informe anual 2025, Balances consolidados, p.649-650 (ES); EUR mn x1,000
A65: TOTAL ASSETS | C65: =SUM(C7,C8,C16,C23,C29,C36,C42,C43,C44,C47,C48,C54,C57,C60,C64) -> 1867515000 | D65: =SUM(D7,D8,D16,D23,D29,D36,D42,D43,D44,D47,D48,D54,D57,D60,D64) -> 1837081000 | E65: =SUM(E7,E8,E16,E23,E29,E36,E42,E43,E44,E47,E48,E54,E57,E60,E64) -> 1797062000 | F65: Note: SUM of top-level asset captions above (formula check)
A66: Per source financial statements (audit check) | C66: 1867515000 | D66: 1837081000 | E66: 1797062000 | F66: Source: Banco Santander, Informe anual 2025, Balances consolidados, p.649-650 (ES); EUR mn x1,000
A67: Variance (computed total vs. source-reported total) | C67: =C65-C66 -> 0 | D67: =D65-D66 -> 0 | E67: =E65-E66 -> 0
A69: LIABILITIES
A70: Financial liabilities held for trading | C70: 171546000 | D70: 152151000 | E70: 122270000 | F70: Source: Banco Santander, Informe anual 2025, Balances consolidados, p.651 (ES); EUR mn x1,000
A71: Derivatives | B71: 9, 11 | C71: 51968000 | D71: 57753000 | E71: 50589000 | F71: Source: Banco Santander, Informe anual 2025, Balances consolidados, p.651 (ES); EUR mn x1,000
A72: Short positions | B72: 9 | C72: 44015000 | D72: 35830000 | E72: 26174000 | F72: Source: Banco Santander, Informe anual 2025, Balances consolidados, p.651 (ES); EUR mn x1,000
A73: Deposits | C73: 75563000 | D73: 58568000 | E73: 45507000 | F73: Source: Banco Santander, Informe anual 2025, Balances consolidados, p.651 (ES); EUR mn x1,000
A74: Central banks | B74: 20 | C74: 12385000 | D74: 13300000 | E74: 7808000 | F74: Source: Banco Santander, Informe anual 2025, Balances consolidados, p.651 (ES); EUR mn x1,000
A75: Credit institutions | B75: 20 | C75: 27058000 | D75: 26284000 | E75: 17862000 | F75: Source: Banco Santander, Informe anual 2025, Balances consolidados, p.651 (ES); EUR mn x1,000
A76: Customers | B76: 21 | C76: 36120000 | D76: 18984000 | E76: 19837000 | F76: Source: Banco Santander, Informe anual 2025, Balances consolidados, p.651 (ES); EUR mn x1,000
A77: Debt securities issued | B77: 22 | C77: 0 | D77: 0 | E77: 0 | F77: Source: Banco Santander, Informe anual 2025, Balances consolidados, p.651 (ES); EUR mn x1,000
A78: Other financial liabilities | B78: 24 | C78: 0 | D78: 0 | E78: 0 | F78: Source: Banco Santander, Informe anual 2025, Balances consolidados, p.651 (ES); EUR mn x1,000
A79: Financial liabilities designated at fair value through profit or loss | C79: 42148000 | D79: 36360000 | E79: 40367000 | F79: Source: Banco Santander, Informe anual 2025, Balances consolidados, p.651 (ES); EUR mn x1,000
A80: Deposits | C80: 30440000 | D80: 28806000 | E80: 34996000 | F80: Source: Banco Santander, Informe anual 2025, Balances consolidados, p.651 (ES); EUR mn x1,000
A81: Central banks | B81: 20 | C81: 3086000 | D81: 1774000 | E81: 1209000 | F81: Source: Banco Santander, Informe anual 2025, Balances consolidados, p.651 (ES); EUR mn x1,000
A82: Credit institutions | B82: 20 | C82: 1424000 | D82: 1625000 | E82: 1735000 | F82: Source: Banco Santander, Informe anual 2025, Balances consolidados, p.651 (ES); EUR mn x1,000
A83: Customers | B83: 21 | C83: 25930000 | D83: 25407000 | E83: 32052000 | F83: Source: Banco Santander, Informe anual 2025, Balances consolidados, p.651 (ES); EUR mn x1,000
A84: Debt securities issued | B84: 22 | C84: 11686000 | D84: 7554000 | E84: 5371000 | F84: Source: Banco Santander, Informe anual 2025, Balances consolidados, p.651 (ES); EUR mn x1,000
A85: Other financial liabilities | B85: 24 | C85: 22000 | D85: 0 | E85: 0 | F85: Source: Banco Santander, Informe anual 2025, Balances consolidados, p.651 (ES); EUR mn x1,000
A86: Memo: subordinated liabilities (included above) | B86: 23 | C86: 0 | D86: 0 | E86: 0 | F86: Source: Banco Santander, Informe anual 2025, Balances consolidados, p.651 (ES); EUR mn x1,000
A87: Financial liabilities at amortised cost | C87: 1421184000 | D87: 1484322000 | E87: 1468703000 | F87: Source: Banco Santander, Informe anual 2025, Balances consolidados, p.651 (ES); EUR mn x1,000
A88: Deposits | C88: 1072384000 | D88: 1126439000 | E88: 1125308000 | F88: Source: Banco Santander, Informe anual 2025, Balances consolidados, p.651 (ES); EUR mn x1,000
A89: Central banks | B89: 20 | C89: 18542000 | D89: 24882000 | E89: 48782000 | F89: Source: Banco Santander, Informe anual 2025, Balances consolidados, p.651 (ES); EUR mn x1,000
A90: Credit institutions | B90: 20 | C90: 74692000 | D90: 90012000 | E90: 81246000 | F90: Source: Banco Santander, Informe anual 2025, Balances consolidados, p.651 (ES); EUR mn x1,000
A91: Customers | B91: 21 | C91: 979150000 | D91: 1011545000 | E91: 995280000 | F91: Source: Banco Santander, Informe anual 2025, Balances consolidados, p.651 (ES); EUR mn x1,000
A92: Debt securities issued | B92: 22 | C92: 312704000 | D92: 317967000 | E92: 303208000 | F92: Source: Banco Santander, Informe anual 2025, Balances consolidados, p.651 (ES); EUR mn x1,000
A93: Other financial liabilities | B93: 24 | C93: 36096000 | D93: 39916000 | E93: 40187000 | F93: Source: Banco Santander, Informe anual 2025, Balances consolidados, p.651 (ES); EUR mn x1,000
A94: Memo: subordinated liabilities (included above) | B94: 23 | C94: 29287000 | D94: 35813000 | E94: 30912000 | F94: Source: Banco Santander, Informe anual 2025, Balances consolidados, p.651 (ES); EUR mn x1,000
A95: Hedging derivatives | B95: 36 | C95: 4248000 | D95: 4752000 | E95: 7656000 | F95: Source: Banco Santander, Informe anual 2025, Balances consolidados, p.651 (ES); EUR mn x1,000
A96: Fair value changes of hedged items in portfolio hedge of interest rate risk | B96: 54 | C96: 49000 | D96: -9000 | E96: 55000 | F96: Source: Banco Santander, Informe anual 2025, Balances consolidados, p.651 (ES); EUR mn x1,000
A97: Liabilities under insurance contracts | B97: 15 | C97: 18737000 | D97: 17829000 | E97: 17799000 | F97: Source: Banco Santander, Informe anual 2025, Balances consolidados, p.651 (ES); EUR mn x1,000
A98: Provisions | C98: 8355000 | D98: 8407000 | E98: 8441000 | F98: Source: Banco Santander, Informe anual 2025, Balances consolidados, p.651 (ES); EUR mn x1,000
A99: Pensions and other post-employment defined benefit obligations | C99: 1656000 | D99: 1731000 | E99: 2225000 | F99: Source: Banco Santander, Informe anual 2025, Balances consolidados, p.651 (ES); EUR mn x1,000
A100: Other long-term employee benefit obligations | C100: 993000 | D100: 915000 | E100: 880000 | F100: Source: Banco Santander, Informe anual 2025, Balances consolidados, p.651 (ES); EUR mn x1,000
A101: Taxes and other legal contingencies | C101: 2989000 | D101: 2717000 | E101: 2715000 | F101: Source: Banco Santander, Informe anual 2025, Balances consolidados, p.651 (ES); EUR mn x1,000
A102: Commitments and guarantees given | C102: 713000 | D102: 710000 | E102: 702000 | F102: Source: Banco Santander, Informe anual 2025, Balances consolidados, p.651 (ES); EUR mn x1,000
...

Sheet Equity Rollforward
A1: Banco Santander — Statement of Total Changes in Consolidated Equity
A2: Detail roll-forward FY2025 and FY2024 — retained earnings tracked separately from net income attributable to the parent (see columns E and I)
A3: Figures in EUR thousands, unless otherwise stated. No decimals shown.
A5: Movement | B5: Capital | C5: Share premium | D5: Other equity instruments | E5: Other equity items | F5: Retained earnings | G5: Revaluation reserves | H5: Other reserves | I5: Treasury shares | J5: Profit attrib. to parent | K5: Interim dividends | L5: Accum. OCI (parent) | M5: NCI - Accum. OCI | N5: NCI - Other items | O5: TOTAL EQUITY
A6: FY2025 MOVEMENT IN EQUITY
A7: Closing balance at 31 December 2024 | B7: 7576000 | C7: 40079000 | D7: 0 | E7: 217000 | F7: 82326000 | G7: 0 | H7: -5976000 | I7: -68000 | J7: 12574000 | K7: -1532000 | L7: -36595000 | M7: -2020000 | N7: 10746000 | O7: 107327000
A8: Effects of correction of errors | B8: 0 | C8: 0 | D8: 0 | E8: 0 | F8: 0 | G8: 0 | H8: 0 | I8: 0 | J8: 0 | K8: 0 | L8: 0 | M8: 0 | N8: 0 | O8: 0
A9: Effects of changes in accounting policies | B9: 0 | C9: 0 | D9: 0 | E9: 0 | F9: 0 | G9: 0 | H9: 0 | I9: 0 | J9: 0 | K9: 0 | L9: 0 | M9: 0 | N9: 0 | O9: 0
A10: Opening balance at 1 January 2025 | B10: 7576000 | C10: 40079000 | D10: 0 | E10: 217000 | F10: 82326000 | G10: 0 | H10: -5976000 | I10: -68000 | J10: 12574000 | K10: -1532000 | L10: -36595000 | M10: -2020000 | N10: 10746000 | O10: 107327000
A11: Total comprehensive income for the year | B11: 0 | C11: 0 | D11: 0 | E11: 0 | F11: 0 | G11: 0 | H11: 0 | I11: 0 | J11: 14101000 | K11: 0 | L11: -1911000 | M11: 53000 | N11: 1399000 | O11: 13642000
A12: Capital reduction | B12: -231000 | C12: -3287000 | D12: 0 | E12: 0 | F12: 0 | G12: 0 | H12: 231000 | I12: 3287000 | J12: 0 | K12: 0 | L12: 0 | M12: 0 | N12: -8000 | O12: -8000
A13: Dividends (shareholder remuneration) | B13: 0 | C13: 0 | D13: 0 | E13: 0 | F13: -1643000 | G13: 0 | H13: 0 | I13: 0 | J13: 0 | K13: -1698000 | L13: 0 | M13: 0 | N13: -896000 | O13: -4237000
A14: Purchase of treasury shares | B14: 0 | C14: 0 | D14: 0 | E14: 0 | F14: 0 | G14: 0 | H14: 0 | I14: -4081000 | J14: 0 | K14: 0 | L14: 0 | M14: 0 | N14: 0 | O14: -4081000
A15: Sale/cancellation of treasury shares | B15: 0 | C15: 0 | D15: 0 | E15: 0 | F15: 0 | G15: 0 | H15: 34000 | I15: 766000 | J15: 0 | K15: 0 | L15: 0 | M15: 0 | N15: 0 | O15: 800000
A16: Transfers between components of equity | B16: 0 | C16: 0 | D16: 0 | E16: 0 | F16: 11276000 | G16: 0 | H16: -766000 | I16: 0 | J16: -12574000 | K16: 1532000 | L16: 532000 | M16: 20000 | N16: -20000 | O16: 0
A17: Business combinations, net | B17: 0 | C17: 0 | D17: 0 | E17: 0 | F17: 0 | G17: 0 | H17: 0 | I17: 0 | J17: 0 | K17: 0 | L17: 0 | M17: 0 | N17: -5000 | O17: -5000
A18: Share-based payments | B18: 0 | C18: 0 | D18: 0 | E18: -67000 | F18: 0 | G18: 0 | H18: 0 | I18: 0 | J18: 0 | K18: 0 | L18: 0 | M18: 0 | N18: 0 | O18: -67000
... A20: Closing balance at 31 December 2025 | B20: 7345000 | C20: 36792000 | D20: 0 | E20: 273000 | F20: 91959000 | G20: 0 | H20: -7532000 | I20: -96000 | J20: 14101000 | K20: -1698000 | L20: -37974000 | M20: -1947000 | N20: 11525000 | O20: 112748000
A21: Source: Banco Santander, Informe anual 2025, Estados totales de cambios en el patrimonio neto consolidados, p.656-661 (ES); EUR mn x1,000
A23: FY2024 MOVEMENT IN EQUITY
A24: Closing balance at 31 December 2023 | B24: 8092000 | C24: 44373000 | D24: 720000 | E24: 195000 | F24: 74114000 | G24: 0 | H24: -5751000 | I24: -1078000 | J24: 11076000 | K24: -1298000 | L24: -35020000 | M24: -1559000 | N24: 10377000 | O24: 104241000
A25: Effects of correction of errors | B25: 0 | C25: 0 | D25: 0 | E25: 0 | F25: 0 | G25: 0 | H25: 0 | I25: 0 | J25: 0 | K25: 0 | L25: 0 | M25: 0 | N25: 0 | O25: 0
A26: Effects of changes in accounting policies | B26: 0 | C26: 0 | D26: 0 | E26: 0 | F26: 0 | G26: 0 | H26: 0 | I26: 0 | J26: 0 | K26: 0 | L26: 0 | M26: 0 | N26: 0 | O26: 0
A27: Opening balance at 1 January 2024 | B27: 8092000 | C27: 44373000 | D27: 720000 | E27: 195000 | F27: 74114000 | G27: 0 | H27: -5751000 | I27: -1078000 | J27: 11076000 | K27: -1298000 | L27: -35020000 | M27: -1559000 | N27: 10377000 | O27: 104241000
A28: Total comprehensive income for the year | B28: 0 | C28: 0 | D28: 0 | E28: 0 | F28: 0 | G28: 0 | H28: 0 | I28: 0 | J28: 12574000 | K28: 0 | L28: -1878000 | M28: -461000 | N28: 1170000 | O28: 11405000
A29: Exercise/maturity of other equity instruments issued | B29: 0 | C29: 0 | D29: -751000 | E29: 0 | F29: 0 | G29: 0 | H29: 0 | I29: 0 | J29: 0 | K29: 0 | L29: 0 | M29: 0 | N29: -590000 | O29: -1341000
A30: Capital reduction | B30: -516000 | C30: -4294000 | D30: 0 | E30: 0 | F30: 0 | G30: 0 | H30: 516000 | I30: 4294000 | J30: 0 | K30: 0 | L30: 0 | M30: 0 | N30: -93000 | O30: -93000
A31: Dividends (shareholder remuneration) | B31: 0 | C31: 0 | D31: 0 | E31: 0 | F31: -1485000 | G31: 0 | H31: 0 | I31: 0 | J31: 0 | K31: -1532000 | L31: 0 | M31: 0 | N31: -660000 | O31: -3677000
A32: Purchase of treasury shares | B32: 0 | C32: 0 | D32: 0 | E32: 0 | F32: 0 | G32: 0 | H32: 0 | I32: -4038000 | J32: 0 | K32: 0 | L32: 0 | M32: 0 | N32: 0 | O32: -4038000
A33: Sale/cancellation of treasury shares | B33: 0 | C33: 0 | D33: 0 | E33: 0 | F33: 0 | G33: 0 | H33: 8000 | I33: 754000 | J33: 0 | K33: 0 | L33: 0 | M33: 0 | N33: 0 | O33: 762000
A34: Transfers between components of equity | B34: 0 | C34: 0 | D34: 0 | E34: 0 | F34: 9697000 | G34: 0 | H34: -215000 | I34: 0 | J34: -11076000 | K34: 1298000 | L34: 303000 | M34: 0 | N34: -7000 | O34: 0
A35: Business combinations, net | B35: 0 | C35: 0 | D35: 0 | E35: 0 | F35: 0 | G35: 0 | H35: 0 | I35: 0 | J35: 0 | K35: 0 | L35: 0 | M35: 0 | N35: -8000 | O35: -8000
... A38: Closing balance at 31 December 2024 | B38: 7576000 | C38: 40079000 | D38: 0 | E38: 217000 | F38: 82326000 | G38: 0 | H38: -5976000 | I38: -68000 | J38: 12574000 | K38: -1532000 | L38: -36595000 | M38: -2020000 | N38: 10746000 | O38: 107327000
A39: Source: Banco Santander, Informe anual 2025, Estados totales de cambios en el patrimonio neto consolidados, p.656-661 (ES); EUR mn x1,000
A41: FY2025 check: Opening balance + all movements (computed) | B41: =B10+B11+B12+B13+B14+B15+B16+B17+B18+B19 -> 7345000 | C41: =C10+C11+C12+C13+C14+C15+C16+C17+C18+C19 -> 36792000 | D41: =D10+D11+D12+D13+D14+D15+D16+D17+D18+D19 -> 0 | E41: =E10+E11+E12+E13+E14+E15+E16+E17+E18+E19 -> 273000 | F41: =F10+F11+F12+F13+F14+F15+F16+F17+F18+F19 -> 91959000 | G41: =G10+G11+G12+G13+G14+G15+G16+G17+G18+G19 -> 0 | H41: =H10+H11+H12+H13+H14+H15+H16+H17+H18+H19 -> -7532000 | I41: =I10+I11+I12+I13+I14+I15+I16+I17+I18+I19 -> -96000 | ... O41: =O10+O11+O12+O13+O14+O15+O16+O17+O18+O19 -> 112748000
A42: FY2025 check: vs. reported closing balance (variance) | B42: =B41-B20 -> 0 | C42: =C41-C20 -> 0 | D42: =D41-D20 -> 0 | E42: =E41-E20 -> 0 | F42: =F41-F20 -> 0 | G42: =G41-G20 -> 0 | H42: =H41-H20 -> 0 | I42: =I41-I20 -> 0 | ... O42: =O41-O20 -> 0
A44: FY2024 check: Opening balance + all movements (computed) | B44: =B27+B28+B29+B30+B31+B32+B33+B34+B35+B36+B37 -> 7576000 | C44: =C27+C28+C29+C30+C31+C32+C33+C34+C35+C36+C37 -> 40079000 | D44: =D27+D28+D29+D30+D31+D32+D33+D34+D35+D36+D37 -> 0 | E44: =E27+E28+E29+E30+E31+E32+E33+E34+E35+E36+E37 -> 217000 | F44: =F27+F28+F29+F30+F31+F32+F33+F34+F35+F36+F37 -> 82326000 | G44: =G27+G28+G29+G30+G31+G32+G33+G34+G35+G36+G37 -> 0 | H44: =H27+H28+H29+H30+H31+H32+H33+H34+H35+H36+H37 -> -5976000 | I44: =I27+I28+I29+I30+I31+I32+I33+I34+I35+I36+I37 -> -68000 | ... O44: =O27+O28+O29+O30+O31+O32+O33+O34+O35+O36+O37 -> 107327000
A45: FY2024 check: vs. reported closing balance (variance) | B45: =B44-B38 -> 0 | C45: =C44-C38 -> 0 | D45: =D44-D38 -> 0 | E45: =E44-E38 -> 0 | F45: =F44-F38 -> 0 | G45: =G44-G38 -> 0 | H45: =H44-H38 -> 0 | I45: =I44-I38 -> 0 | ... O45: =O44-O38 -> 0

Sheet Indirect Cash Flow
A1: Banco Santander — Indirect Consolidated Cash Flow Statement (reconstructed)
A2: Years ended 31 December 2025 and 2024 — built entirely from P&L, Balance Sheet and Equity Rollforward formulas; the published cash flow statement was NOT used as a source (see Cover & Methodology, notes 5 and 6)
A3: Figures in EUR thousands, unless otherwise stated. No decimals shown.
A5: Line item | B5: FY2025 | C5: FY2024 | D5: Methodology / source
A6: OPERATING ACTIVITIES
A7: Profit for the year (consolidated, before split between parent and non-controlling interests) | B7: ='P&L'!C49 -> 15500000 | C7: ='P&L'!D49 -> 13744000 | D7: Linked from P&L tab. This is the IAS 7 indirect-method starting point.
A8: Adjustments for non-cash items classified as investing (avoids double-counting vs. the working-capital section below — see Cover & Methodology, note 6)
A9: Add back: Depreciation and amortisation | B9: =-('P&L'!C32) -> 3178000 | C9: =-('P&L'!D32) -> 3179000 | D9: Reverses the non-cash P&L charge; the real cash effect is rebuilt in the investing section as part of the fixed-asset capex/disposal proxy.
A10: Add back: Impairment of non-financial assets | B10: =-('P&L'!C38) -> 251000 | C10: =-('P&L'!D38) -> 624000 | D10: Reverses the non-cash P&L charge; rebuilt in the investing fixed-asset proxy.
A11: Less: Share of results of entities under the equity method | B11: =-('P&L'!C13) -> -665000 | C11: =-('P&L'!D13) -> -687000 | D11: Non-cash income from associates/JVs; the cash proxy (income less net movement in the investment) is rebuilt in the investing section.
A12: Less: Gains on derecognition of non-financial assets, net | B12: =-('P&L'!C42) -> 0 | C12: =-('P&L'!D42) -> -368000 | D12: Relates to disposals of tangible/intangible assets; rebuilt in the investing fixed-asset proxy.
A13: Less: Negative goodwill recognised in profit or loss | B13: =-('P&L'!C43) -> -22000 | C13: =-('P&L'!D43) -> 0 | D13: Relates to business combinations; not a cash item.
A14: Less: Gains/(losses) from non-current assets held for sale not classified as discontinued operations | B14: =-('P&L'!C44) -> -226000 | C14: =-('P&L'!D44) -> 27000 | D14: Relates to the disposal-group reclassification; rebuilt in the investing section. See note 5 on the Cover & Methodology tab.
A15: Cash flow from operations before changes in operating assets and liabilities | B15: =SUM(B7:B14) -> 18016000 | C15: =SUM(C7:C14) -> 16519000 | D15: Subtotal: profit for the year plus/less the non-cash items above.
A16: Changes in operating assets and liabilities, net (period-over-period Balance Sheet movement; increase in an asset uses cash, increase in a liability is a source of cash)
A17: (Increase)/decrease in financial assets held for trading | B17: =-('Balance Sheet'!C8-'Balance Sheet'!D8) -> -22065000 | C17: =-('Balance Sheet'!D8-'Balance Sheet'!E8) -> -53332000 | D17: Balance Sheet movement, trading book.
A18: (Increase)/decrease in non-trading financial assets mandatorily at FVTPL | B18: =-('Balance Sheet'!C16-'Balance Sheet'!D16) -> -1631000 | C18: =-('Balance Sheet'!D16-'Balance Sheet'!E16) -> -220000 | D18: Balance Sheet movement.
A19: (Increase)/decrease in financial assets designated at FVTPL | B19: =-('Balance Sheet'!C23-'Balance Sheet'!D23) -> -131000 | C19: =-('Balance Sheet'!D23-'Balance Sheet'!E23) -> 1858000 | D19: Balance Sheet movement.
A20: (Increase)/decrease in financial assets at fair value through OCI | B20: =-('Balance Sheet'!C29-'Balance Sheet'!D29) -> 15286000 | C20: =-('Balance Sheet'!D29-'Balance Sheet'!E29) -> -6590000 | D20: Balance Sheet movement.
A21: (Increase)/decrease in financial assets at amortised cost (loans and advances to banks/customers, debt securities) | B21: =-('Balance Sheet'!C36-'Balance Sheet'!D36) -> 1018000 | C21: =-('Balance Sheet'!D36-'Balance Sheet'!E36) -> -12304000 | D21: Balance Sheet movement, net of impairment already embedded in the carrying amount (no separate impairment add-back — see note 6).
A22: (Increase)/decrease in hedging derivatives (asset) | B22: =-('Balance Sheet'!C42-'Balance Sheet'!D42) -> 1741000 | C22: =-('Balance Sheet'!D42-'Balance Sheet'!E42) -> -375000 | D22: Balance Sheet movement.
A23: (Increase)/decrease in fair value changes of hedged items (asset) | B23: =-('Balance Sheet'!C43-'Balance Sheet'!D43) -> -754000 | C23: =-('Balance Sheet'!D43-'Balance Sheet'!E43) -> -84000 | D23: Balance Sheet movement.
A24: (Increase)/decrease in assets under reinsurance contracts | B24: =-('Balance Sheet'!C47-'Balance Sheet'!D47) -> -1000 | C24: =-('Balance Sheet'!D47-'Balance Sheet'!E47) -> 15000 | D24: Balance Sheet movement.
A25: (Increase)/decrease in other assets | B25: =-('Balance Sheet'!C60-'Balance Sheet'!D60) -> -160000 | C25: =-('Balance Sheet'!D60-'Balance Sheet'!E60) -> 297000 | D25: Balance Sheet movement.
A26: (Increase)/decrease in tax assets | B26: =-('Balance Sheet'!C57-'Balance Sheet'!D57) -> 520000 | C26: =-('Balance Sheet'!D57-'Balance Sheet'!E57) -> 794000 | D26: Balance Sheet movement, current and deferred combined.
A27: Increase/(decrease) in financial liabilities held for trading | B27: ='Balance Sheet'!C70-'Balance Sheet'!D70 -> 19395000 | C27: ='Balance Sheet'!D70-'Balance Sheet'!E70 -> 29881000 | D27: Balance Sheet movement, trading book.
A28: Increase/(decrease) in financial liabilities designated at FVTPL, deposits and other (excl. debt securities issued, classified as financing) | B28: =('Balance Sheet'!C79-'Balance Sheet'!D79)-('Balance Sheet'!C84-'Balance Sheet'!D84) -> 1656000 | C28: =('Balance Sheet'!D79-'Balance Sheet'!E79)-('Balance Sheet'!D84-'Balance Sheet'!E84) -> -6190000 | D28: Category total less its 'Debt securities issued' component, which is classified as financing below.
A29: Increase/(decrease) in financial liabilities at amortised cost, deposits and other (excl. debt securities issued, classified as financing) | B29: =('Balance Sheet'!C87-'Balance Sheet'!D87)-('Balance Sheet'!C92-'Balance Sheet'!D92) -> -57875000 | C29: =('Balance Sheet'!D87-'Balance Sheet'!E87)-('Balance Sheet'!D92-'Balance Sheet'!E92) -> 860000 | D29: Category total less its 'Debt securities issued' component (customer/interbank deposits are the dominant driver here).
A30: Increase/(decrease) in hedging derivatives (liability) | B30: ='Balance Sheet'!C95-'Balance Sheet'!D95 -> -504000 | C30: ='Balance Sheet'!D95-'Balance Sheet'!E95 -> -2904000 | D30: Balance Sheet movement.
A31: Increase/(decrease) in fair value changes of hedged items (liability) | B31: ='Balance Sheet'!C96-'Balance Sheet'!D96 -> 58000 | C31: ='Balance Sheet'!D96-'Balance Sheet'!E96 -> -64000 | D31: Balance Sheet movement.
A32: Increase/(decrease) in liabilities under insurance contracts | B32: ='Balance Sheet'!C97-'Balance Sheet'!D97 -> 908000 | C32: ='Balance Sheet'!D97-'Balance Sheet'!E97 -> 30000 | D32: Balance Sheet movement.
A33: Increase/(decrease) in provisions | B33: ='Balance Sheet'!C98-'Balance Sheet'!D98 -> -52000 | C33: ='Balance Sheet'!D98-'Balance Sheet'!E98 -> -34000 | D33: Balance Sheet movement, net of the P&L provision charge already embedded in the closing balance (no separate provision-charge add-back — see note 6).
A34: Increase/(decrease) in tax liabilities | B34: ='Balance Sheet'!C104-'Balance Sheet'!D104 -> -30000 | C34: ='Balance Sheet'!D104-'Balance Sheet'!E104 -> -334000 | D34: Balance Sheet movement, current and deferred combined.
A35: Increase/(decrease) in other liabilities | B35: ='Balance Sheet'!C107-'Balance Sheet'!D107 -> -407000 | C35: ='Balance Sheet'!D107-'Balance Sheet'!E107 -> -1254000 | D35: Balance Sheet movement.
A36: Total changes in operating assets and liabilities, net | B36: =SUM(B17:B35) -> -43028000 | C36: =SUM(C17:C35) -> -49950000 | D36: Subtotal of the working-capital movements above.
A37: NET CASH FLOW FROM OPERATING ACTIVITIES | B37: =B15+B36 -> -25012000 | C37: =C15+C36 -> -33431000 | D37: Formula: Cash flow before working-capital changes, plus total working-capital changes.
A38: INVESTING ACTIVITIES
A39: Net cash flow relating to investments in joint ventures and associates | B39: =('P&L'!C13)-('Balance Sheet'!C44-'Balance Sheet'!D44) -> 890000 | C39: =('P&L'!D13)-('Balance Sheet'!D44-'Balance Sheet'!E44) -> 1056000 | D39: Proxy for dividends received less net new investment = equity-method income for the year less the net movement in the investment's carrying value (BS). Assumes no unseparated FX/impairment noise in this specific line; a genuine limitation given no further disclosure is available.
A40: Net investment in tangible and intangible fixed assets (capex, disposals, depreciation, amortisation and impairment, net) | B40: =-(('Balance Sheet'!C48-'Balance Sheet'!D48)+('Balance Sheet'!C54-'Balance Sheet'!D54))+('P&L'!C32)+('P&L'!C38) -> 3171000 | C40: =-(('Balance Sheet'!D48-'Balance Sheet'!E48)+('Balance Sheet'!D54-'Balance Sheet'!E54))+('P&L'!D32)+('P&L'!D38) -> -1396000 | D40: Tangible and intangible assets (incl. goodwill) are combined because the source does not disclose depreciation/amortisation split by asset class on the face of the statements (see note 6). Formula: -(Δ Tangible NBV + Δ Intangible NBV) + D&A + non-financial impairment.
A41: Net movement in non-current assets and disposal groups held for sale, net of associated liabilities | B41: =-('Balance Sheet'!C64-'Balance Sheet'!D64)+('Balance Sheet'!C108-'Balance Sheet'!D108) -> -8014000 | C41: =-('Balance Sheet'!D64-'Balance Sheet'!E64)+('Balance Sheet'!D108-'Balance Sheet'!E108) -> -988000 | D41: This is the single largest driver of the 'Unreconciled balance' below: the EUR 71.0bn increase in disposal-group assets in 2025 is predominantly a Balance Sheet RECLASSIFICATION (assets regrouped ahead of a pending disposal), not a cash movement, but this cannot be separated from genuine investing cash flow without the Group's own published cash flow statement, which was deliberately not used here. See Cover & Methodology, note 5.
A42: NET CASH FLOW FROM/(USED IN) INVESTING ACTIVITIES | B42: =SUM(B39:B41) -> -3953000 | C42: =SUM(C39:C41) -> -1328000 | D42: Subtotal of the investing lines above.
A43: FINANCING ACTIVITIES
A44: Net issuance/(repayment) of debt securities issued (wholesale funding) | B44: =('Balance Sheet'!C77-'Balance Sheet'!D77)+('Balance Sheet'!C84-'Balance Sheet'!D84)+('Balance Sheet'!C92-'Balance Sheet'!D92) -> -1131000 | C44: =('Balance Sheet'!D77-'Balance Sheet'!E77)+('Balance Sheet'!D84-'Balance Sheet'!E84)+('Balance Sheet'!D92-'Balance Sheet'!E92) -> 16942000 | D44: Sum of the 'Debt securities issued' balance across all three liability categories on the Balance Sheet tab.
A45: Capital reduction (net equity impact) | B45: ='Equity Rollforward'!O12 -> -8000 | C45: ='Equity Rollforward'!O30 -> -93000 | D45: Linked from Equity Rollforward, 'TOTAL EQUITY' column. Mostly a non-cash cancellation of already-repurchased treasury shares; the cash outflow itself is captured in the treasury-share purchase line below.
A46: Dividends paid (to owners of the parent and non-controlling interests) | B46: ='Equity Rollforward'!O13 -> -4237000 | C46: ='Equity Rollforward'!O31 -> -3677000 | D46: Linked from Equity Rollforward.
A47: Purchase of treasury shares | B47: ='Equity Rollforward'!O14 -> -4081000 | C47: ='Equity Rollforward'!O32 -> -4038000 | D47: Linked from Equity Rollforward.
A48: Sale/cancellation of treasury shares | B48: ='Equity Rollforward'!O15 -> 800000 | C48: ='Equity Rollforward'!O33 -> 762000 | D48: Linked from Equity Rollforward.
A49: Redemption/exercise of other equity instruments (e.g. AT1 capital instruments) | B49: =0 -> 0 | C49: ='Equity Rollforward'!O29 -> -1341000 | D49: Linked from Equity Rollforward (zero in FY2025; a EUR 1,341m AT1-type redemption in FY2024).
A50: Business combinations, net (non-controlling interest impact) | B50: ='Equity Rollforward'!O17 -> -5000 | C50: ='Equity Rollforward'!O35 -> -8000 | D50: Linked from Equity Rollforward.
A51: Other equity movements, net | B51: ='Equity Rollforward'!O19 -> -623000 | C51: ='Equity Rollforward'!O37 -> 138000 | D51: Linked from Equity Rollforward; residual second-order equity items (e.g. non-controlling interest transactions) not separately identified in the source.
A52: Memo (excluded, non-cash, not in the sum below): share-based payments and transfers between equity components
A53: NET CASH FLOW FROM/(USED IN) FINANCING ACTIVITIES | B53: =SUM(B44:B51) -> -9285000 | C53: =SUM(C44:C51) -> 8685000 | D53: Subtotal of the financing lines above.
A54: RECONCILIATION TO REPORTED CASH
A55: Net cash flow before unreconciled balance | B55: =B37+B42+B53 -> -38250000 | C55: =C37+C42+C53 -> -26074000 | D55: Formula: Operating + Investing + Financing net cash flow, as reconstructed above.
A56: Actual change in cash and cash equivalents (per Balance Sheet) | B56: ='Balance Sheet'!C7-'Balance Sheet'!D7 -> -39927000 | C56: ='Balance Sheet'!D7-'Balance Sheet'!E7 -> -28134000 | D56: Linked from the Balance Sheet tab cash line.
A57: Unreconciled balance (bridge to reported cash movement) — see Cover & Methodology, note 5 | B57: =B56-B55 -> -1677000 | C57: =C56-C55 -> -2060000 | D57: Formula: Actual Balance Sheet cash movement LESS the net cash flow reconstructed above. Not an invented figure — it is the formula-computed residual, isolated here (rather than allocated across causes we cannot separately quantify) precisely so the model still ties to reported cash. See Cover & Methodology, note 5 for the drivers we believe explain most of this line.
A58: NET INCREASE/(DECREASE) IN CASH AND CASH EQUIVALENTS | B58: =B55+B57 -> -39927000 | C58: =C55+C57 -> -28134000 | D58: Formula: Net cash flow before unreconciled balance, plus the bridge line (equals the actual Balance Sheet cash movement by construction).
A59: Cash and cash equivalents at beginning of year | B59: ='Balance Sheet'!D7 -> 192208000 | C59: ='Balance Sheet'!E7 -> 220342000 | D59: Linked from the Balance Sheet tab, prior-year column.
A60: Cash and cash equivalents at end of year | B60: =B59+B58 -> 152281000 | C60: =C59+C58 -> 192208000 | D60: Formula: Opening cash plus the net increase/(decrease) for the year.
A61: Check: closing cash per this statement vs. Balance Sheet (should equal zero) | B61: =B60-'Balance Sheet'!C7 -> 0 | C61: =C60-'Balance Sheet'!D7 -> 0 | D61: By construction (via the bridge line above) this is always zero.

Sheet Direct Cash Flow
A1: Banco Santander — Direct Consolidated Cash Flow Statement (reconstructed)
A2: Years ended 31 December 2025 and 2024 — operating section built from income-statement accrual proxies; investing, financing and the reconciliation to reported cash are linked from the Indirect Cash Flow tab, since IAS 7 only allows the two methods to differ in how operating activities are presented
A3: Figures in EUR thousands, unless otherwise stated. No decimals shown.
A5: Line item | B5: FY2025 | C5: FY2024 | D5: Methodology / source
A6: OPERATING ACTIVITIES (direct method — income-statement accrual used as a cash proxy where a genuine cash-received/cash-paid figure is not separately disclosed)
A7: Interest received | B7: ='P&L'!C6 -> 101710000 | C7: ='P&L'!D6 -> 109012000 | D7: Proxy: income-statement accrual (interest income). No separate cash-basis interest disclosure exists in the source statements.
A8: Interest paid | B8: ='P&L'!C10 -> -59362000 | C8: ='P&L'!D10 -> -65225000 | D8: Proxy: income-statement accrual (interest expense).
A9: Dividends received | B9: ='P&L'!C12 -> 715000 | C9: ='P&L'!D12 -> 710000 | D9: Linked from P&L.
A10: Fee and commission income received | B10: ='P&L'!C14 -> 17387000 | C10: ='P&L'!D14 -> 16834000 | D10: Linked from P&L.
A11: Fee and commission expense paid | B11: ='P&L'!C15 -> -4411000 | C11: ='P&L'!D15 -> -4458000 | D11: Linked from P&L.
A12: Net gains/(losses) on financial transactions received/(paid) | B12: =('P&L'!C16)+('P&L'!C19)+('P&L'!C20)+('P&L'!C21)+('P&L'!C22) -> 1955000 | C12: =('P&L'!D16)+('P&L'!D19)+('P&L'!D20)+('P&L'!D21)+('P&L'!D22) -> 2427000 | D12: Sum of 5 trading/FV P&L lines. Linked from P&L.
A13: Net exchange differences | B13: ='P&L'!C23 -> 407000 | C13: ='P&L'!D23 -> -216000 | D13: Linked from P&L.
A14: Other operating income received | B14: ='P&L'!C24 -> 1583000 | C14: ='P&L'!D24 -> 846000 | D14: Linked from P&L.
A15: Other operating expenses paid | B15: ='P&L'!C25 -> -2070000 | C15: ='P&L'!D25 -> -2258000 | D15: Linked from P&L.
A16: Net income/(expense) from insurance and reinsurance contracts | B16: =('P&L'!C26)+('P&L'!C27) -> 91000 | C16: =('P&L'!D26)+('P&L'!D27) -> 21000 | D16: Linked from P&L.
A17: Cash paid to employees and suppliers (administrative expenses) | B17: ='P&L'!C29 -> -21533000 | C17: ='P&L'!D29 -> -21970000 | D17: Proxy: income-statement accrual (staff + other administrative expenses).
A18: Net provisions charged (accrual proxy) | B18: ='P&L'!C33 -> -2729000 | C18: ='P&L'!D33 -> -3465000 | D18: Accrual proxy only — the true cash effect is captured in 'changes in operating assets and liabilities' below (linked from the Indirect tab), which nets this accrual against the actual Balance Sheet provision movement so the two are not double-counted.
A19: Impairment losses on financial assets, net (accrual proxy) | B19: ='P&L'!C34 -> -12546000 | C19: ='P&L'!D34 -> -12136000 | D19: Accrual proxy only — true cash effect captured in 'changes in operating assets and liabilities' below.
A20: Income tax paid (accrual proxy) | B20: ='P&L'!C46 -> -4723000 | C20: ='P&L'!D46 -> -4844000 | D20: Proxy: income-statement accrual. No separate cash-tax-paid disclosure exists in the source.
A21: Profit after tax from discontinued operations (accrual proxy) | B21: ='P&L'!C48 -> 1542000 | C21: ='P&L'!D48 -> 1241000 | D21: Linked from P&L.
A22: Cash flow from operating activities before changes in operating assets and liabilities | B22: =SUM(B7:B21) -> 18016000 | C22: =SUM(C7:C21) -> 16519000 | D22: Subtotal of the direct-method lines above. By construction this equals the equivalent pre-working-capital subtotal on the Indirect Cash Flow tab — both are derived from the same P&L, just regrouped differently (see the cross-check row below).
A23: Changes in operating assets and liabilities, net (linked from Indirect Cash Flow tab) | B23: ='Indirect Cash Flow'!B36 -> -43028000 | C23: ='Indirect Cash Flow'!C36 -> -49950000 | D23: Single source of truth: identical working-capital methodology under both the direct and indirect method, so this line is linked rather than rebuilt.
A24: NET CASH FLOW FROM OPERATING ACTIVITIES | B24: =B22+B23 -> -25012000 | C24: =C22+C23 -> -33431000 | D24: Formula: Cash flow before working-capital changes, plus the working-capital changes above.
A25: Cross-check: vs. Indirect Cash Flow tab operating total (should equal zero — true identity, not a plug) | B25: =B24-'Indirect Cash Flow'!B37 -> 0 | C25: =C24-'Indirect Cash Flow'!C37 -> 0 | D25: Both methods are built from the same source data and must tie exactly by construction.
A26: INVESTING ACTIVITIES (linked from Indirect Cash Flow tab — identical under both methods)
A27: Net cash flow relating to investments in joint ventures and associates | B27: ='Indirect Cash Flow'!B39 -> 890000 | C27: ='Indirect Cash Flow'!C39 -> 1056000 | D27: Linked from Indirect Cash Flow tab.
A28: Net investment in tangible and intangible fixed assets, net | B28: ='Indirect Cash Flow'!B40 -> 3171000 | C28: ='Indirect Cash Flow'!C40 -> -1396000 | D28: Linked from Indirect Cash Flow tab.
A29: Net movement in non-current assets and disposal groups held for sale, net of associated liabilities | B29: ='Indirect Cash Flow'!B41 -> -8014000 | C29: ='Indirect Cash Flow'!C41 -> -988000 | D29: Linked from Indirect Cash Flow tab. See Cover & Methodology, note 5.
A30: NET CASH FLOW FROM/(USED IN) INVESTING ACTIVITIES | B30: =SUM(B27:B29) -> -3953000 | C30: =SUM(C27:C29) -> -1328000 | D30: Subtotal of the investing lines above.
A31: FINANCING ACTIVITIES (linked from Indirect Cash Flow tab — identical under both methods)
A32: Net issuance/(repayment) of debt securities issued (wholesale funding) | B32: ='Indirect Cash Flow'!B44 -> -1131000 | C32: ='Indirect Cash Flow'!C44 -> 16942000 | D32: Linked from Indirect Cash Flow tab.
A33: Capital reduction (net equity impact) | B33: ='Indirect Cash Flow'!B45 -> -8000 | C33: ='Indirect Cash Flow'!C45 -> -93000 | D33: Linked from Indirect Cash Flow tab.
A34: Dividends paid (to owners of the parent and non-controlling interests) | B34: ='Indirect Cash Flow'!B46 -> -4237000 | C34: ='Indirect Cash Flow'!C46 -> -3677000 | D34: Linked from Indirect Cash Flow tab.
A35: Purchase of treasury shares | B35: ='Indirect Cash Flow'!B47 -> -4081000 | C35: ='Indirect Cash Flow'!C47 -> -4038000 | D35: Linked from Indirect Cash Flow tab.
A36: Sale/cancellation of treasury shares | B36: ='Indirect Cash Flow'!B48 -> 800000 | C36: ='Indirect Cash Flow'!C48 -> 762000 | D36: Linked from Indirect Cash Flow tab.
A37: Redemption/exercise of other equity instruments (e.g. AT1 capital instruments) | B37: ='Indirect Cash Flow'!B49 -> 0 | C37: ='Indirect Cash Flow'!C49 -> -1341000 | D37: Linked from Indirect Cash Flow tab.
A38: Business combinations, net (non-controlling interest impact) | B38: ='Indirect Cash Flow'!B50 -> -5000 | C38: ='Indirect Cash Flow'!C50 -> -8000 | D38: Linked from Indirect Cash Flow tab.
A39: Other equity movements, net | B39: ='Indirect Cash Flow'!B51 -> -623000 | C39: ='Indirect Cash Flow'!C51 -> 138000 | D39: Linked from Indirect Cash Flow tab.
A40: NET CASH FLOW FROM/(USED IN) FINANCING ACTIVITIES | B40: =SUM(B32:B39) -> -9285000 | C40: =SUM(C32:C39) -> 8685000 | D40: Subtotal of the financing lines above.
A41: RECONCILIATION TO REPORTED CASH (linked from Indirect Cash Flow tab)
A42: Net cash flow before unreconciled balance | B42: =B24+B30+B40 -> -38250000 | C42: =C24+C30+C40 -> -26074000 | D42: Formula: Operating + Investing + Financing net cash flow, as reconstructed above.
A43: Actual change in cash and cash equivalents (per Balance Sheet) | B43: ='Indirect Cash Flow'!B56 -> -39927000 | C43: ='Indirect Cash Flow'!C56 -> -28134000 | D43: Linked from Indirect Cash Flow tab.
A44: Unreconciled balance (bridge to reported cash movement) — see Cover & Methodology, note 5 | B44: =B43-B42 -> -1677000 | C44: =C43-C42 -> -2060000 | D44: Formula: Actual Balance Sheet cash movement LESS the net cash flow reconstructed above (see the Indirect Cash Flow tab and Cover & Methodology, note 5, for the same figure and its drivers — the direct and indirect methods necessarily carry the same unreconciled amount, since both tie to the same reported Balance Sheet cash balance).
A45: NET INCREASE/(DECREASE) IN CASH AND CASH EQUIVALENTS | B45: =B42+B44 -> -39927000 | C45: =C42+C44 -> -28134000 | D45: Formula: Net cash flow before unreconciled balance, plus the bridge line.
A46: Cash and cash equivalents at beginning of year | B46: ='Indirect Cash Flow'!B59 -> 192208000 | C46: ='Indirect Cash Flow'!C59 -> 220342000 | D46: Linked from Indirect Cash Flow tab.
A47: Cash and cash equivalents at end of year | B47: =B46+B45 -> 152281000 | C47: =C46+C45 -> 192208000 | D47: Formula: Opening cash plus the net increase/(decrease) for the year.
A48: Check: closing cash per this statement vs. Balance Sheet (should equal zero) | B48: =B47-'Balance Sheet'!C7 -> 0 | C48: =C47-'Balance Sheet'!D7 -> 0 | D48: By construction (via the bridge line above) this is always zero, in both the direct and the indirect statement.
