Workbook

Sheet Income Statement
A1: INDITEX — CONSOLIDATED INCOME STATEMENT (P&L)
A2: FY2025 (Feb 1, 2025 - Jan 31, 2026) | Amounts in EUR millions unless noted
A4: Item | B4: FY2025 | C4: FY2024 | D4: Change (abs.) | E4: Change (%)
A5: Net sales | B5: 39864 | C5: 38632 | D5: =IF(B5="","",B5-C5) -> 1232 | E5: =IF(OR(B5="",C5=0),"",B5/C5-1) -> 0.031890661
A6: Gross profit | B6: 23222 | C6: 22343 | D6: =IF(B6="","",B6-C6) -> 879 | E6: =IF(OR(B6="",C6=0),"",B6/C6-1) -> 0.039341181
A7: EBITDA | B7: 11267 | C7: 10730 | D7: =IF(B7="","",B7-C7) -> 537 | E7: =IF(OR(B7="",C7=0),"",B7/C7-1) -> 0.050046598
A8: EBIT (operating profit) | B8: 7997 | C8: 7551 | D8: =IF(B8="","",B8-C8) -> 446 | E8: =IF(OR(B8="",C8=0),"",B8/C8-1) -> 0.059065025
A9: Profit before tax (PBT) | C9: 7577 | D9: =IF(B9="","",B9-C9) | E9: =IF(OR(B9="",C9=0),"",B9/C9-1)
A10: Net income | B10: 6220 | C10: 5866 | D10: =IF(B10="","",B10-C10) -> 354 | E10: =IF(OR(B10="",C10=0),"",B10/C10-1) -> 0.060347767
A12: Ratios (% of sales)
A13: Gross margin % of sales | B13: =B6/B5 -> 0.5825306 | C13: =C6/C5 -> 0.57835473
A14: EBITDA margin % of sales | B14: =B7/B5 -> 0.28263596 | C14: =C7/C5 -> 0.27774902
A15: EBIT margin % of sales | B15: =B8/B5 -> 0.20060706 | C15: =C8/C5 -> 0.19545972
A16: Net margin % of sales | B16: =B10/B5 -> 0.1560305 | C16: =C10/C5 -> 0.15184303
A18: Other KPIs
A19: Earnings per share (EPS), EUR | B19: 1.996 | C19: 1.884 | D19: =B19-C19 -> 0.112 | E19: =B19/C19-1 -> 0.059447983
A20: Dividend per share, EUR | B20: 1.75 | C20: 1.68 | D20: =B20-C20 -> 0.07 | E20: =B20/C20-1 -> 0.041666667
A21: Net cash position (EURm) | B21: 10958 | C21: 11495 | D21: =B21-C21 -> -537 | E21: =B21/C21-1 -> -0.046715963
A24: Source: Inditex, "Consolidated Results FY2025" (Feb 1, 2025 - Jan 31, 2026), published at inditex.com/press, March 2026. FY2025 PBT was not disclosed in the summary report reviewed; FY2024 EBIT is estimated from the reported FY2024 PBT (EUR 7,577m).

Sheet Balance Sheet
A1: INDITEX — CONSOLIDATED BALANCE SHEET
A2: As of January 31, 2026 and January 31, 2025 | Amounts in EUR millions
A4: Item | B4: 01/31/2026 | C4: 01/31/2025
A5: ASSETS
A6: Non-current assets
A7: Right-of-use assets | B7: 5542 | C7: 5269
A8: Intangible assets | B8: 1840 | C8: 1607
A9: Property, plant and equipment | B9: 11142 | C9: 10014
A10: Financial investments | B10: 471 | C10: 450
A11: Other non-current assets | B11: 952 | C11: 1017
A12: Total non-current assets | B12: =SUM(B7:B11) -> 19947 | C12: =SUM(C7:C11) -> 18357
A13: Current assets
A14: Inventories | B14: 3249 | C14: 3321
A15: Trade and other receivables | B15: 1166 | C15: 1088
A16: Short-term financial investments | B16: 5684 | C16: 5120
A17: Cash and cash equivalents | B17: 5276 | C17: 6382
A18: Other current assets | B18: 316 | C18: 445
A19: Total current assets | B19: =SUM(B14:B18) -> 15691 | C19: =SUM(C14:C18) -> 16356
A20: TOTAL ASSETS | B20: =B12+B19 -> 35638 | C20: =C12+C19 -> 34713
A22: LIABILITIES AND EQUITY
A23: Equity
A24: Share capital | B24: 94 | C24: 94
A25: Share premium | B25: 20 | C25: 20
A26: Retained earnings (prior years, accumulated) | B26: 13605 | C26: 13128
A27: Net income for the year | B27: 6220 | C27: 5866
A28: Treasury shares | B28: -7 | C28: -47
A29: Accumulated other comprehensive income (translation differences, hedges, etc.) | B29: 463 | C29: 615
A30: Minority interests | B30: 0 | C30: 0
A31: Total equity | B31: =SUM(B24:B30) -> 20395 | C31: =SUM(C24:C30) -> 19676
A32: Non-current liabilities (estimated) | B32: 5071 | C32: 4850
A33: Current liabilities (estimated) | B33: 10172 | C33: 10187
A34: TOTAL LIABILITIES AND EQUITY | B34: =B31+B32+B33 -> 35638 | C34: =C31+C32+C33 -> 34713
A36: Check (Total Assets - Total Liabilities and Equity) | B36: =B20-B34 -> 0 | C36: =C20-C34 -> 0
A38: Other year-end data
A39: Net cash position | B39: 10958 | C39: 11495
A40: Number of stores | B40: 5460 | C40: 5563
A43: Source (Assets): Inditex, "Consolidated Results FY2025" (year-end Jan 31, 2026), inditex.com/press, March 2026. Source (Equity detail): reclassification of market data (Investing.com historical ITX balance sheet), which groups share capital + share premium, retained earnings, treasury shares, accumulated other comprehensive income and minority interests; exact line items in Inditex's audited Consolidated Financial Statements may differ slightly in naming. Retained earnings has been split into prior-years accumulated earnings and net income for the year by subtracting the reported net income of each year from the combined 'retained earnings' balance reported by the market data source; this is an approximation (it does not net out dividends paid) and should be confirmed against Inditex's audited FY2025 Consolidated Financial Statements (inditex.com). The full official breakdown of non-current and current liabilities as of 01/31/2026 was not available in the summary report reviewed; both figures are estimates adjusted to balance the sheet and should likewise be confirmed against the audited financial statements.

Sheet Cash Flow (Indirect)
A1: INDITEX — CONSOLIDATED CASH FLOW STATEMENT (INDIRECT METHOD)
A2: FY2025 (Feb 1, 2025 - Jan 31, 2026) | EUR millions | Built by Claude from the Income Statement and Balance Sheet tabs via formulas — NOT taken from Inditex's published cash flow statement. Gross capex and lease-liability repayments are estimated using a D&A allocation (see Memo block); short-term financial investments are treated as cash equivalents, consistent with Inditex's own 'Net cash position' KPI. Single period only (two balance sheet dates available).
A4: Item | B4: FY2025 (EURm) | C4: Basis / derivation
A5: OPERATING ACTIVITIES
A6: Net income | B6: ='Income Statement'!B10 -> 6220 | C6: Income Statement, Net income
A7: Depreciation and amortization (add-back, total) | B7: ='Income Statement'!B7-'Income Statement'!B8 -> 3270 | C7: Income Statement, EBITDA - EBIT
A8: (Increase)/decrease in inventories | B8: ='Balance Sheet'!C14-'Balance Sheet'!B14 -> 72 | C8: Balance Sheet, prior Inventories - current Inventories
A9: (Increase)/decrease in trade and other receivables | B9: ='Balance Sheet'!C15-'Balance Sheet'!B15 -> -78 | C9: Balance Sheet, prior Receivables - current Receivables
A10: (Increase)/decrease in other current assets | B10: ='Balance Sheet'!C18-'Balance Sheet'!B18 -> 129 | C10: Balance Sheet, prior Other current assets - current
A11: (Increase)/decrease in other non-current assets | B11: ='Balance Sheet'!C11-'Balance Sheet'!B11 -> 65 | C11: Balance Sheet, prior Other non-current assets - current
A12: Increase/(decrease) in current liabilities (trade payables & other, proxy) | B12: ='Balance Sheet'!B33-'Balance Sheet'!C33 -> -15 | C12: Balance Sheet, current Current liabilities - prior (single estimated line; no payables/accruals split available)
A13: Net cash from operating activities | B13: =SUM(B6:B12) -> 9663
A15: MEMO — SUPPORTING CALCULATIONS FOR INVESTING & FINANCING ESTIMATES
A16: Average right-of-use (ROU) asset balance | B16: =AVERAGE('Balance Sheet'!B7,'Balance Sheet'!C7) -> 5405.5 | C16: Balance Sheet, average of ROU assets at both year-ends
A17: Average property, plant & equipment (PP&E) balance | B17: =AVERAGE('Balance Sheet'!B9,'Balance Sheet'!C9) -> 10578 | C17: Balance Sheet, average of PP&E at both year-ends
A18: Average intangible assets balance | B18: =AVERAGE('Balance Sheet'!B8,'Balance Sheet'!C8) -> 1723.5 | C18: Balance Sheet, average of Intangible assets at both year-ends
A19: Estimated D&A allocated to ROU assets | B19: =B7*(B16/(B16+B17+B18)) -> 998.24843 | C19: Total D&A x [avg ROU / (avg ROU + avg PP&E + avg Intangibles)] — allocates total D&A across asset classes in proportion to their average balance, since Inditex does not separately disclose D&A by asset class in the summary results reviewed
A20: Estimated D&A allocated to PP&E & intangible assets | B20: =B7-B19 -> 2271.7516 | C20: Total D&A - D&A allocated to ROU assets
A21: Estimated gross capex in PP&E & intangible assets | B21: =(('Balance Sheet'!B9-'Balance Sheet'!C9)+('Balance Sheet'!B8-'Balance Sheet'!C8))+B20 -> 3632.7516 | C21: Δ Net book value of PP&E + Intangibles, plus the D&A allocated to them (since Net BV(end) = Net BV(beg) + Capex - D&A, so Capex = ΔNet BV + D&A)
A22: Estimated repayment of lease liabilities (principal portion) | B22: =B19 -> 998.24843 | C22: Proxy = D&A allocated to ROU assets (a common simplifying approximation for the annual cash principal repaid on lease liabilities, absent a separate lease-liability disclosure)
A24: INVESTING ACTIVITIES
A25: Purchases of property, plant & equipment and intangible assets (estimated gross capex) | B25: =-B21 -> -3632.7516 | C25: -(Estimated gross capex, see Memo block above)
A26: Net investment in financial assets, non-current | B26: =-('Balance Sheet'!B10-'Balance Sheet'!C10) -> -21 | C26: -(Δ Financial investments, non-current). Short-term financial investments are excluded here and treated as cash equivalents (see Financing section below and Inditex's own 'Net cash position' KPI, which nets cash + short-term financial investments)
A27: Net cash used in investing activities | B27: =SUM(B25:B26) -> -3653.7516
A29: FINANCING ACTIVITIES
A30: Dividends paid (implied from retained earnings roll-forward) | B30: =-('Balance Sheet'!C26+'Balance Sheet'!C27-'Balance Sheet'!B26) -> -5389 | C30: -(prior Retained earnings + prior Net income - current Retained earnings); i.e. implied payout consistent with the equity roll-forward
A31: Repayment of lease liabilities (principal portion, estimated) | B31: =-B22 -> -998.24843 | C31: -(Estimated lease liability repayment, see Memo block above)
A32: Change in treasury shares | B32: ='Balance Sheet'!B28-'Balance Sheet'!C28 -> 40 | C32: Balance Sheet, Δ Treasury shares
A33: Change in accumulated other comprehensive income (translation/hedges, net) | B33: ='Balance Sheet'!B29-'Balance Sheet'!C29 -> -152 | C33: Balance Sheet, Δ Accumulated other comprehensive income
A34: Change in minority interests | B34: ='Balance Sheet'!B30-'Balance Sheet'!C30 -> 0 | C34: Balance Sheet, Δ Minority interests
A35: Other financing and reconciling items, net (balancing item) | B35: =(('Balance Sheet'!B17+'Balance Sheet'!B16)-('Balance Sheet'!C17+'Balance Sheet'!C16))-(B13+B27+SUM(B30:B34)) -> -52 | C35: Balancing item = reported Δ (cash + short-term financial investments) - all other operating, investing and financing lines above. With gross capex and lease repayments now estimated explicitly (see Memo block), this residual is much smaller and mainly reflects remaining estimation noise from the Balance Sheet tab's own Non-current/Current liabilities estimates, plus items with no visibility in the summarized statements (e.g. share-based compensation, provisions, minor FX effects)
A36: Net cash from/(used in) financing activities | B36: =SUM(B30:B35) -> -6551.2484
A38: NET INCREASE/(DECREASE) IN CASH AND CASH EQUIVALENTS (broad: cash + ST financial investments) | B38: =B13+B27+B36 -> -542
A39: Cash and cash equivalents at beginning of year (broad: cash + ST financial investments) | B39: ='Balance Sheet'!C17+'Balance Sheet'!C16 -> 11502 | C39: Balance Sheet, Cash + Short-term financial investments (01/31/2025)
A40: Cash and cash equivalents at end of year (broad) | B40: =B38+B39 -> 10960
A41: Check vs. reported ending cash + ST financial investments (Balance Sheet) | B41: =B40-('Balance Sheet'!B17+'Balance Sheet'!B16) -> 0 | C41: Should equal zero by construction (the plug above forces this)
A44: Methodology note: this cash flow statement is not published by Inditex; it is derived entirely within this workbook by linking Balance Sheet changes (01/31/2026 vs. 01/31/2025) and Income Statement items via the formulas shown in column B. Gross capex and lease-liability repayments — the two largest cash items missing from a simple balance-sheet-delta approach for a lease-heavy retailer like Inditex — are estimated by allocating total D&A (EBITDA - EBIT) between ROU assets and PP&E/intangibles in proportion to their average balances (see the Memo block), then adding it back to the respective net book value change. Short-term financial investments are treated as cash equivalents, matching Inditex's own disclosed 'Net cash position' metric (cash + short-term financial investments, net of financial debt). Because only two year-end balance sheet snapshots are available and the Non-current/Current liabilities split in the Balance Sheet tab is itself an estimate, a small 'Other financing and reconciling items, net' line absorbs the remaining gap so the statement ties exactly to the reported change in cash. Treat this as an illustrative, internally-consistent model, not a substitute for Inditex's audited consolidated cash flow statement.

Sheet Cash Flow (Direct)
A1: INDITEX — CONSOLIDATED CASH FLOW STATEMENT (DIRECT METHOD)
A2: FY2025 (Feb 1, 2025 - Jan 31, 2026) | EUR millions | Built by Claude from the Income Statement and Balance Sheet tabs via formulas — NOT taken from Inditex's published cash flow statement. The operating section is presented on a direct-method basis; Investing and Financing sections link to the 'Cash Flow (Indirect)' tab (including its D&A-allocation-based capex and lease-repayment estimates), since those two sections are identical under both methods by definition.
A4: Item | B4: FY2025 (EURm) | C4: Basis / derivation
A5: OPERATING ACTIVITIES
A6: Cash received from customers | B6: ='Income Statement'!B5-('Balance Sheet'!B15-'Balance Sheet'!C15) -> 39786 | C6: Net sales - Δ Receivables (increase in receivables reduces cash collected)
A7: Cash paid to suppliers/vendors | B7: =-(('Income Statement'!B5-'Income Statement'!B7)+('Balance Sheet'!B14-'Balance Sheet'!C14)-('Balance Sheet'!B33-'Balance Sheet'!C33)+('Balance Sheet'!B18-'Balance Sheet'!C18)+('Balance Sheet'!B11-'Balance Sheet'!C11)) -> -28346 | C7: -(Total cash operating costs [Net sales - EBITDA, i.e. COGS + all opex excl. D&A] + Δ Inventories - Δ Current liabilities [payables proxy] + Δ Other current assets + Δ Other non-current assets); combines goods and operating-expense payments to suppliers/vendors into a single line
A8: Income taxes and other operating items, net (balancing item) | B8: ='Cash Flow (Indirect)'!B13-SUM(B6:B7) -> -1777 | C8: Balancing item = Net cash from operating activities per the indirect method (linked from the 'Cash Flow (Indirect)' tab) minus the two direct-method lines above; approximates cash income taxes paid plus any other operating cash items not separately visible in the summarized statements
A9: Net cash from operating activities | B9: =SUM(B6:B8) -> 9663
A11: INVESTING ACTIVITIES (linked from Cash Flow (Indirect) tab)
A12: Purchases of property, plant & equipment and intangible assets (estimated gross capex) | B12: ='Cash Flow (Indirect)'!B25 -> -3632.7516 | C12: Linked from 'Cash Flow (Indirect)' tab (identical under both methods)
A13: Net investment in financial assets, non-current | B13: ='Cash Flow (Indirect)'!B26 -> -21 | C13: Linked from 'Cash Flow (Indirect)' tab (identical under both methods)
A14: Net cash used in investing activities | B14: =SUM(B12:B13) -> -3653.7516
A16: FINANCING ACTIVITIES (linked from Cash Flow (Indirect) tab)
A17: Dividends paid (implied from retained earnings roll-forward) | B17: ='Cash Flow (Indirect)'!B30 -> -5389 | C17: Linked from 'Cash Flow (Indirect)' tab (identical under both methods)
A18: Repayment of lease liabilities (principal portion, estimated) | B18: ='Cash Flow (Indirect)'!B31 -> -998.24843 | C18: Linked from 'Cash Flow (Indirect)' tab (identical under both methods)
A19: Change in treasury shares | B19: ='Cash Flow (Indirect)'!B32 -> 40 | C19: Linked from 'Cash Flow (Indirect)' tab (identical under both methods)
A20: Change in accumulated other comprehensive income (translation/hedges, net) | B20: ='Cash Flow (Indirect)'!B33 -> -152 | C20: Linked from 'Cash Flow (Indirect)' tab (identical under both methods)
A21: Change in minority interests | B21: ='Cash Flow (Indirect)'!B34 -> 0 | C21: Linked from 'Cash Flow (Indirect)' tab (identical under both methods)
A22: Other financing and reconciling items, net (balancing item) | B22: ='Cash Flow (Indirect)'!B35 -> -52 | C22: Linked from 'Cash Flow (Indirect)' tab (identical under both methods)
A23: Net cash from/(used in) financing activities | B23: =SUM(B17:B22) -> -6551.2484
A25: NET INCREASE/(DECREASE) IN CASH AND CASH EQUIVALENTS (broad: cash + ST financial investments) | B25: =B9+B14+B23 -> -542
A26: Cash and cash equivalents at beginning of year (broad: cash + ST financial investments) | B26: ='Balance Sheet'!C17+'Balance Sheet'!C16 -> 11502 | C26: Balance Sheet, Cash + Short-term financial investments (01/31/2025)
A27: Cash and cash equivalents at end of year (broad) | B27: =B25+B26 -> 10960
A28: Check vs. reported ending cash + ST financial investments (Balance Sheet) | B28: =B27-('Balance Sheet'!B17+'Balance Sheet'!B16) -> 0 | C28: Should equal zero by construction
A29: Check vs. Net cash from operating activities (Indirect method) | B29: =B9-'Cash Flow (Indirect)'!B13 -> 0 | C29: Should equal zero — both methods must produce the same operating total
A32: Methodology note: as required by accounting standards, the direct and indirect methods must report the same 'Net cash from operating activities' and identical investing/financing sections — only the presentation of the operating section differs. 'Cash paid to suppliers/vendors' combines both cost of goods and operating expenses paid (i.e. all cash operating costs before D&A), adjusted for the related working-capital movements; the residual needed to match the indirect-method operating total is shown as 'Income taxes and other operating items, net'. Investing and Financing sections — including the D&A-allocation-based gross capex and lease-repayment estimates — are linked from the 'Cash Flow (Indirect)' tab; see that tab's Memo block and methodology note for how those estimates are derived. This is an illustrative, internally-consistent model built for this workbook — not Inditex's audited, published cash flow statement.
